track4px/__init__.py
track4px/classes/__init__.py
track4px/classes/api.py
track4px/classes/http.py
track4px/classes/shipment.py
track4px-0.1.0.dist-info/METADATA
track4px-0.1.0.dist-info/WHEEL
track4px-0.1.0.dist-info/licenses/LICENSE
track4px-0.1.0.dist-info/RECORD
