Metadata-Version: 2.3
Name: track4px
Version: 0.1.0
Summary: Simple Python wrapper to fetch parcel tracking data from 4PX
Project-URL: Homepage, https://git.private.coffee/kumi/track4px
Project-URL: Bug Tracker, https://git.private.coffee/kumi/track4px/issues
Author-email: Kumi Mitterer <dpdtrack@kumi.email>
License: Copyright (c) 2024 Kumi Mitterer <track4px@kumi.email>
License-File: LICENSE
Classifier: License :: OSI Approved :: MIT License
Classifier: Operating System :: OS Independent
Classifier: Programming Language :: Python :: 3
Requires-Python: >=3.10
